sdh/otl/__init__.py
sdh/otl/generator.py
sdh/otl/urls.py
sdh/otl/views.py
sdh_otl-1.0.1.dist-info/licenses/LICENSE
sdh_otl-1.0.1.dist-info/METADATA
sdh_otl-1.0.1.dist-info/WHEEL
sdh_otl-1.0.1.dist-info/top_level.txt
sdh_otl-1.0.1.dist-info/RECORD
