Metadata-Version: 2.4
Name: sdh.otl
Version: 1.0.1
Summary: Django one time link generator and processor
Author-email: Viacheslav Vic Bukhantsov <vic.bukhantsov@gmail.com>, "Oleksii (Alex) Koval" <alex@koval.kharkov.ua>
Maintainer-email: Viacheslav Vic Bukhantsov <vic.bukhantsov@gmail.com>
License-Expression: BSD-2-Clause
Project-URL: Repository, https://github.com/sdh-global/sdh-otl
Classifier: Development Status :: 5 - Production/Stable
Classifier: Intended Audience :: Developers
Classifier: Framework :: Django
Classifier: Operating System :: OS Independent
Classifier: Programming Language :: Python
Classifier: Programming Language :: Python :: 3
Classifier: Programming Language :: Python :: 3.8
Classifier: Programming Language :: Python :: 3.9
Classifier: Programming Language :: Python :: 3.10
Classifier: Programming Language :: Python :: 3.11
Classifier: Topic :: Internet :: WWW/HTTP :: Dynamic Content
Classifier: Topic :: Software Development
Classifier: Topic :: Software Development :: Libraries
Requires-Python: >=3.8
License-File: LICENSE
Requires-Dist: Django>=3.2
Dynamic: license-file
